RPA/LiteLLM.py
rpaframework_litellm-0.1.2.dist-info/LICENSE
rpaframework_litellm-0.1.2.dist-info/METADATA
rpaframework_litellm-0.1.2.dist-info/WHEEL
rpaframework_litellm-0.1.2.dist-info/RECORD
